examples/persistent_index.py
examples/preprocessing.py
examples/quickstart.py
tests/__init__.py
tests/test_core.py
tests/test_variants.py
yabm25/__init__.py
yabm25/core.py
yabm25/index.py
yabm25/utils.py
yabm25/variants.py
yabm25/version.py
yabm25-0.1.1.dist-info/LICENSE
yabm25-0.1.1.dist-info/METADATA
yabm25-0.1.1.dist-info/WHEEL
yabm25-0.1.1.dist-info/top_level.txt
yabm25-0.1.1.dist-info/RECORD
