Metadata-Version: 2.2
Name: yabm25
Version: 0.1.1
Summary: Fast BM25 search engine for Python with RAG support
Author-email: Ali Muhammad <ali@quantlix.com>
License: MIT
Project-URL: Documentation, https://yabm25.quantlix.com/
Project-URL: Source, https://github.com/alimuhammadofficial/yabm25
Project-URL: Issues, https://github.com/alimuhammadofficial/yabm25/issues
Keywords: bm25,search-engine,ranking,information-retrieval,rag,llm,vector-search,elastic-search,ranking-algorithm,nltk,transformers,huggingface,langchain,llamaindex
Classifier: Development Status :: 4 - Beta
Classifier: Intended Audience :: Developers
Classifier: Intended Audience :: Science/Research
Classifier: Intended Audience :: Information Technology
Classifier: Topic :: Scientific/Engineering :: Artificial Intelligence
Classifier: Topic :: Text Processing :: Indexing
Classifier: Topic :: Software Development :: Libraries :: Python Modules
Classifier: Programming Language :: Python :: 3
Classifier: Programming Language :: Python :: 3.8
Classifier: Programming Language :: Python :: 3.9
Classifier: Programming Language :: Python :: 3.10
Classifier: Programming Language :: Python :: 3.11
Classifier: Programming Language :: Python :: 3.12
Classifier: License :: OSI Approved :: MIT License
Classifier: Operating System :: OS Independent
Requires-Python: >=3.8
License-File: LICENSE
Requires-Dist: numpy>=1.20.0
Requires-Dist: pyarrow>=7.0.0
Provides-Extra: dev
Requires-Dist: pytest>=7.0; extra == "dev"
Requires-Dist: black>=22.0; extra == "dev"
Requires-Dist: build; extra == "dev"
Requires-Dist: twine; extra == "dev"
Requires-Dist: pytest-cov>=4.1.0; extra == "dev"
